tkSDLImg/__init__.py
tkSDLImg/py.typed
tksdlimg-0.0.3.dist-info/licenses/LICENSE
tksdlimg-0.0.3.dist-info/METADATA
tksdlimg-0.0.3.dist-info/WHEEL
tksdlimg-0.0.3.dist-info/top_level.txt
tksdlimg-0.0.3.dist-info/RECORD
